Metadata-Version: 1.1
Name: pydealer
Version: 1.4.0
Summary: A package for constructing decks of playing cards, for games.
Home-page: https://github.com/Trebek/pydealer
Author: Alex Crawford
Author-email: kebert406@yahoo.com
License: GPLv3
Download-URL: https://pypi.python.org/pypi/pydealer
Keywords: playing cards deck games french standard 52 poker blackjack
Platform: UNKNOWN
Classifier: Development Status :: 4 - Beta
Classifier: License :: OSI Approved :: GNU General Public License v3 (GPLv3)
Classifier: Topic :: Games/Entertainment
Classifier: Topic :: Utilities
Classifier: Programming Language :: Python :: 2.6
Classifier: Programming Language :: Python :: 2.7
Classifier: Programming Language :: Python :: 3
Classifier: Programming Language :: Python :: 3.1
Classifier: Programming Language :: Python :: 3.2
Classifier: Programming Language :: Python :: 3.3
